<annotation>
	<folder>20241021_inet_real_images</folder>
	<filename>20241021fpa_1_03171.jpg</filename>
	<path>I:\アノテーション\FPA\annotations\ym_20241129\ym_20241129\base\20241105-01_train-valid\20241021_inet_real_images\20241021fpa_1_03171.jpg</path>
	<source>
		<database>Unknown</database>
	</source>
	<size>
		<width>1392</width>
		<height>784</height>
		<depth>3</depth>
	</size>
	<segmented>0</segmented>
	<object>
		<name>flame</name>
		<pose>Unspecified</pose>
		<truncated>0</truncated>
		<difficult>0</difficult>
		<bndbox>
			<xmin>723</xmin>
			<ymin>345</ymin>
			<xmax>786</xmax>
			<ymax>474</ymax>
		</bndbox>
	</object>
	<object>
		<name>black_smoke</name>
		<pose>Unspecified</pose>
		<truncated>0</truncated>
		<difficult>0</difficult>
		<bndbox>
			<xmin>54</xmin>
			<ymin>235</ymin>
			<xmax>514</xmax>
			<ymax>554</ymax>
		</bndbox>
	</object>
	<object>
		<name>sf</name>
		<pose>Unspecified</pose>
		<truncated>0</truncated>
		<difficult>0</difficult>
		<bndbox>
			<xmin>5</xmin>
			<ymin>5</ymin>
			<xmax>856</xmax>
			<ymax>592</ymax>
		</bndbox>
	</object>
</annotation>
