<annotation>
	<folder>kasai_real</folder>
	<filename>kasai_real_3140.png</filename>
	<path>C:\Users\eartheyes\Documents\アノテーション\清水建設\まとめ\real1\kasai_real\kasai_real_3140.png</path>
	<source>
		<database>Unknown</database>
	</source>
	<size>
		<width>1920</width>
		<height>1080</height>
		<depth>3</depth>
	</size>
	<segmented>0</segmented>
	<object>
		<name>fire</name>
		<pose>Unspecified</pose>
		<truncated>0</truncated>
		<difficult>0</difficult>
		<bndbox>
			<xmin>474</xmin>
			<ymin>567</ymin>
			<xmax>605</xmax>
			<ymax>653</ymax>
		</bndbox>
	</object>
	<object>
		<name>sqwatting_person</name>
		<pose>Unspecified</pose>
		<truncated>1</truncated>
		<difficult>0</difficult>
		<bndbox>
			<xmin>694</xmin>
			<ymin>963</ymin>
			<xmax>845</xmax>
			<ymax>1080</ymax>
		</bndbox>
	</object>
	<object>
		<name>sqwatting_person</name>
		<pose>Unspecified</pose>
		<truncated>1</truncated>
		<difficult>0</difficult>
		<bndbox>
			<xmin>879</xmin>
			<ymin>882</ymin>
			<xmax>1063</xmax>
			<ymax>1080</ymax>
		</bndbox>
	</object>
	<object>
		<name>standing_person</name>
		<pose>Unspecified</pose>
		<truncated>0</truncated>
		<difficult>0</difficult>
		<bndbox>
			<xmin>1559</xmin>
			<ymin>581</ymin>
			<xmax>1610</xmax>
			<ymax>772</ymax>
		</bndbox>
	</object>
	<object>
		<name>standing_person</name>
		<pose>Unspecified</pose>
		<truncated>0</truncated>
		<difficult>0</difficult>
		<bndbox>
			<xmin>1543</xmin>
			<ymin>577</ymin>
			<xmax>1572</xmax>
			<ymax>641</ymax>
		</bndbox>
	</object>
</annotation>
